torusgrid/__callbacks.py
torusgrid/__init__.py
torusgrid/_field_util.py
torusgrid/core/__init__.py
torusgrid/core/consts.py
torusgrid/core/data.py
torusgrid/core/dtypes.py
torusgrid/core/fourier.py
torusgrid/core/generics.py
torusgrid/core/version.py
torusgrid/dynamics/__init__.py
torusgrid/dynamics/base.py
torusgrid/dynamics/hooks/__init__.py
torusgrid/dynamics/hooks/base.py
torusgrid/dynamics/hooks/default.py
torusgrid/dynamics/hooks/display.py
torusgrid/dynamics/hooks/earlystop.py
torusgrid/dynamics/hooks/interrupt.py
torusgrid/dynamics/hooks/monitor.py
torusgrid/dynamics/special/__init__.py
torusgrid/dynamics/special/rk4.py
torusgrid/dynamics/special/split.py
torusgrid/dynamics/special/temporal.py
torusgrid/dynamics/util/__init__.py
torusgrid/dynamics/util/history.py
torusgrid/fields/_1d.py
torusgrid/fields/_2d.py
torusgrid/fields/__init__.py
torusgrid/fields/_base.py
torusgrid/fields/_complex.py
torusgrid/fields/_real.py
torusgrid/fields/_util.py
torusgrid/grids/_1d.py
torusgrid/grids/_2d.py
torusgrid/grids/__init__.py
torusgrid/grids/_base.py
torusgrid/grids/_complex.py
torusgrid/grids/_real.py
torusgrid/grids/_util.py
torusgrid/misc/__init__.py
torusgrid/misc/console.py
torusgrid/misc/context.py
torusgrid/misc/testutils/__init__.py
torusgrid/misc/testutils/asserts.py
torusgrid/misc/testutils/common.py
torusgrid/misc/testutils/dtype.py
torusgrid/misc/testutils/gen.py
torusgrid/misc/testutils/pytest.py
torusgrid/proxies/__init__.py
torusgrid/proxies/_fields.py
torusgrid/proxies/_grids.py
torusgrid/transforms/__init__.py
torusgrid/transforms/field.py
torusgrid/transforms/grid.py
torusgrid/utils/__init__.py
torusgrid/utils/io.py
torusgrid/utils/plot.py
torusgrid-0.4.8.dist-info/LICENSE
torusgrid-0.4.8.dist-info/METADATA
torusgrid-0.4.8.dist-info/WHEEL
torusgrid-0.4.8.dist-info/top_level.txt
torusgrid-0.4.8.dist-info/RECORD
