Metadata-Version: 2.1
Name: torusgrid
Version: 0.4.8
Summary: periodic fields with definite dimensions equipped with FFT operations
Home-page: https://github.com/michael-960/torusgrid
Author: Michael Wang
Author-email: mike.wang96029@gmail.com
Project-URL: Bug Tracker, https://github.com/michael-960/torusgrid/issues
Classifier: Programming Language :: Python :: 3
Classifier: License :: OSI Approved :: MIT License
Classifier: Operating System :: OS Independent
Requires-Python: >=3.7
License-File: LICENSE
Requires-Dist: numpy (>=1.21.2)
Requires-Dist: pyfftw (>=0.12.0)
Requires-Dist: matplotlib (>=3.5.1)
Requires-Dist: scikit-image (>=0.19.0)
Requires-Dist: rich (>=12.4.0)
